.hgignore
.hgtags
CHANGES.txt
LICENSE.txt
README.txt
bootstrap.py
buildout.cfg
setup.py
src/ws/__init__.py
src/ws.dependencychecker.egg-info/PKG-INFO
src/ws.dependencychecker.egg-info/SOURCES.txt
src/ws.dependencychecker.egg-info/dependency_links.txt
src/ws.dependencychecker.egg-info/entry_points.txt
src/ws.dependencychecker.egg-info/namespace_packages.txt
src/ws.dependencychecker.egg-info/not-zip-safe
src/ws.dependencychecker.egg-info/requires.txt
src/ws.dependencychecker.egg-info/top_level.txt
src/ws/dependencychecker/__init__.py
src/ws/dependencychecker/check.py
src/ws/dependencychecker/main.py
src/ws/dependencychecker/modules.cfg
src/ws/dependencychecker/parse.py
src/ws/dependencychecker/tests/__init__.py
src/ws/dependencychecker/tests/test_check.py
src/ws/dependencychecker/tests/test_parse.py
src/ws/dependencychecker/tests/fixtures/invalid.py
src/ws/dependencychecker/tests/fixtures/invalid.zcml
src/ws/dependencychecker/tests/fixtures/valid.py
src/ws/dependencychecker/tests/fixtures/valid.zcml