Metadata-Version: 1.0
Name: ws.dependencychecker
Version: 1.1
Summary: Checks whether imported packages are declared in setup.py
